README.md
setup.py
proio/__init__.py
proio/event.py
proio/reader.py
proio/writer.py
proio.egg-info/PKG-INFO
proio.egg-info/SOURCES.txt
proio.egg-info/dependency_links.txt
proio.egg-info/requires.txt
proio.egg-info/top_level.txt
proio.egg-info/zip-safe
proio/model/__init__.py
proio/model/eic/__init__.py
proio/model/eic/eic_pb2.py
proio/model/example/__init__.py
proio/model/example/example_pb2.py
proio/model/lcio/__init__.py
proio/model/lcio/lcio_pb2.py
proio/model/mc/__init__.py
proio/model/mc/mc_pb2.py
proio/proto/__init__.py
proio/proto/proio_pb2.py
tests/__init__.py
tests/test_files.py
tests/test_metadata.py
tests/test_push_get.py
tests/test_ref_deref.py
tests/test_tags.py