Metadata-Version: 1.0
Name: proio
Version: 0.12.196
Summary: Library for reading and writing proio files and streams
Home-page: http://github.com/proio-org/py-proio
Author: David Blyth
Author-email: dblyth@anl.gov
License: BSD-3-Clause
Platform: UNKNOWN
